[
 {
  "agency": "굿리치",
  "hq": "굿리치",
  "branch": "리치강북센터지점",
  "start": "2019-11-22",
  "fp": 0,
  "tel": "02-6410-7336",
  "addr": "서울 강북구 도봉로 308 (번1동,북한산스카이빌딩) 15층",
  "addr_raw": "(010-62) 서울 강북구 도봉로 308 (번1동,북한산스카이빌딩) 15층",
  "visits": 1
 },
 {
  "agency": "굿리치",
  "hq": "굿리치",
  "branch": "위드사업부지점",
  "start": "2024-06-24",
  "fp": 0,
  "tel": "070-4416-4016",
  "addr": "서울 강북구 인수봉로37길 2 (수유1동) 203호",
  "addr_raw": "(010-95) 서울 강북구 인수봉로37길 2 (수유1동) 203호",
  "visits": 0
 },
 {
  "agency": "글로벌금융판매",
  "hq": "글로벌금융판매 케이에스금융씨브",
  "branch": "케이에스에프에스공자",
  "start": "2023-02-13",
  "fp": 4,
  "tel": "",
  "addr": "서울 종로구 난계로29가길 17 (숭인2동) 익성씨티하임오피스텔, 202-비호",
  "addr_raw": "(031-16) 서울 종로구 난계29가길 17 (숭인2동) 익성씨티하임오피스텔, 202-비호",
  "visits": 1
 },
 {
  "agency": "글로벌금융판매",
  "hq": "글로벌금융판매 케이에스금융씨브",
  "branch": "케이에스에프에스동대문",
  "start": "2020-04-22",
  "fp": 4,
  "tel": "",
  "addr": "서울 종로구 난계로29가길 17 (숭인2동) 익성씨티하임오피스텔, 202-에이호",
  "addr_raw": "(031-16) 서울 종로구 난계29가길 17 (숭인2동) 익성씨티하임오피스텔, 202-에이호",
  "visits": 1
 },
 {
  "agency": "더블유에셋",
  "hq": "더블유에셋",
  "branch": "부자자산관리지점",
  "start": "2020-12-10",
  "fp": 2,
  "tel": "02-6952-9997",
  "addr": "서울 동대문구 고미술로 99 (답십리2동) 226호",
  "addr_raw": "(026-22) 서울 동대문구 고미술로 99 (답십리2동) 226호",
  "visits": 1
 },
 {
  "agency": "더블유에셋",
  "hq": "더블유에셋",
  "branch": "한결지사",
  "start": "2024-01-22",
  "fp": 5,
  "tel": "02-2277-7767",
  "addr": "서울 종로구 종로 222 (종로5가,광동빌딩) 312호",
  "addr_raw": "(031-96) 서울 종로구 종로 222 (종로5가,광동빌딩) 312호",
  "visits": 0
 },
 {
  "agency": "리더스에셋어드바이저",
  "hq": "리더스에셋어드바이저",
  "branch": "스페셜",
  "start": "2020-04-08",
  "fp": 1,
  "tel": "010-4226-5130",
  "addr": "서울특별시 성동구 왕십리로 386 별관402호(하왕십리동,삼협빌딩)",
  "addr_raw": "(047-01) 서울특별시 성동구 왕십리로 386 별관402호(하왕십리동,삼협빌딩)",
  "visits": 1
 },
 {
  "agency": "메가",
  "hq": "메가한강금융",
  "branch": "메가인슈에셋그린",
  "start": "2019-08-18",
  "fp": 10,
  "tel": "02-2638-0052",
  "addr": "서울 종로구 종로 19 (종로1가,르메이에르종로타워) B동 11층 1116호",
  "addr_raw": "(031-57) 서울 종로구 종로 19 (종로1가,르메이에르종로타워) B동 11층 1116호",
  "visits": 1
 },
 {
  "agency": "메가",
  "hq": "메가한강금융",
  "branch": "메가한강금융",
  "start": "2019-08-18",
  "fp": 5,
  "tel": "02-2138-7930",
  "addr": "서울 동대문구 천호대로83길 3 (장안1동,포유존) 201호",
  "addr_raw": "(026-36) 서울 동대문구 천호대로83길 3 (장안1동,포유존) 201호",
  "visits": 1
 },
 {
  "agency": "삼성법인",
  "hq": "삼성법인",
  "branch": "삼성인슈지점",
  "start": "2023-09-01",
  "fp": 8,
  "tel": "032-324-9119",
  "addr": "서울 동대문구 고산자로 406 (용두동,화성빌딩) 604호",
  "addr_raw": "(025-65) 서울 동대문구 고산자로 406 (용두동,화성빌딩) 604호",
  "visits": 0
 },
 {
  "agency": "삼성법인",
  "hq": "삼성법인",
  "branch": "중앙총괄지점",
  "start": "2023-09-01",
  "fp": 17,
  "tel": "02-2088-3552",
  "addr": "서울 종로구 우정국로 45-11 (수송동) 1층",
  "addr_raw": "(031-50) 서울 종로구 우정국로 45-11 (수송동) 1층",
  "visits": 1
 },
 {
  "agency": "신한금융플러스",
  "hq": "신한금융플러스",
  "branch": "기업금융지점",
  "start": "2021-04-02",
  "fp": 4,
  "tel": "02-723-7329",
  "addr": "서울특별시 종로구 새문안로3길 30 909호 (내수동,대우빌딩)",
  "addr_raw": "(031-73) 서울특별시 종로구 새문안로3길 30 909호 (내수동,대우빌딩)",
  "visits": 1
 },
 {
  "agency": "신한금융플러스",
  "hq": "신한금융플러스",
  "branch": "서울중앙지점",
  "start": "2021-03-04",
  "fp": 1,
  "tel": "010-2701-9407",
  "addr": "서울 중랑구 동일로157길 19 (묵2동,기영빌딩) 366호",
  "addr_raw": "(020-09) 서울 중랑구 동일로157길 19 (묵2동,기영빌딩) 366호",
  "visits": 0
 },
 {
  "agency": "아너스금융서비스",
  "hq": "우리사업부",
  "branch": "경희",
  "start": "2022-10-09",
  "fp": 5,
  "tel": "02-921-4590",
  "addr": "서울 동대문구 무학로36길 34 (용두동) 4층",
  "addr_raw": "(025-85) 서울 동대문구 무학로36길 34 (용두동) 4층",
  "visits": 0
 },
 {
  "agency": "아너스금융서비스",
  "hq": "퍼스트에셋",
  "branch": "씨앤아이에셋누리",
  "start": "2019-08-19",
  "fp": 1,
  "tel": "02-468-4449",
  "addr": "서울 노원구 동일로 986 노원프레미어스앰코 101동 205-A",
  "addr_raw": "(018-49) 서울 노원구 동일로 986 노원프레미어스앰코 101동 205-A",
  "visits": 0
 },
 {
  "agency": "아너스금융서비스",
  "hq": "퍼스트에셋",
  "branch": "한주에셋",
  "start": "2019-08-19",
  "fp": 5,
  "tel": "02-997-5276",
  "addr": "서울시 강북구 노해로 41, 401호(수유동, 동아빌딩)",
  "addr_raw": "(010-77) 서울시 강북구 노해로 41, 401호(수유동, 동아빌딩)",
  "visits": 1
 },
 {
  "agency": "에이비에이금융서비스",
  "hq": "에이비에이금융서비스",
  "branch": "종로지사",
  "start": "2025-08-18",
  "fp": 4,
  "tel": "02-765-0123",
  "addr": "서울 성북구 보문로 119-1 (보문동2가) 2층 202호",
  "addr_raw": "(028-71) 서울 성북구 보문로 119-1 (보문동2가) 2층 202호",
  "visits": 1
 },
 {
  "agency": "에이원금융판매",
  "hq": "에이원금융판매",
  "branch": "비즈스타",
  "start": "2024-12-23",
  "fp": 2,
  "tel": "02-0927-1357",
  "addr": "서울 동대문구 한천로2길 77 (장안1동,대월빌딩) 3층 A-02호",
  "addr_raw": "(026-34) 서울 동대문구 한천로2길 77 (장안1동,대월빌딩) 3층 A-02호",
  "visits": 1
 },
 {
  "agency": "엠금융서비스",
  "hq": "글로벌코리아사업부",
  "branch": "온누리자산관리",
  "start": "2024-02-28",
  "fp": 6,
  "tel": "02-446-1777",
  "addr": "서울 강북구 수유로 36 (수유1동,이화빌딩) 401호",
  "addr_raw": "(011-12) 서울 강북구 수유로 36 (수유1동,이화빌딩) 401호",
  "visits": 1
 },
 {
  "agency": "엠금융서비스",
  "hq": "리더스재무설계사업부",
  "branch": "드림",
  "start": "2014-05-29",
  "fp": 2,
  "tel": "02-7450-0771",
  "addr": "서울 성북구 창경궁로 324 303호 (삼선동1가,삼선교복합건물)",
  "addr_raw": "(028-66) 서울 성북구 창경궁로 324 303호 (삼선동1가,삼선교복합건물)",
  "visits": 1
 },
 {
  "agency": "오지에이",
  "hq": "오지에이",
  "branch": "(주)오지에이보험대리점 성북",
  "start": "2021-10-13",
  "fp": 9,
  "tel": "02-987-1316",
  "addr": "서울 성북구 동소문로 305-1 (길음2동,레츠키즈빌딩) 2층",
  "addr_raw": "(027-30) 서울 성북구 동소문로 305-1 (길음2동,레츠키즈빌딩) 2층",
  "visits": 1
 },
 {
  "agency": "오지에이",
  "hq": "오지에이",
  "branch": "서진",
  "start": "2014-05-20",
  "fp": 2,
  "tel": "02-3291-9080",
  "addr": "서울 동대문구 천호대로 23 820호 (신설동,베르빌오피스텔)",
  "addr_raw": "(025-82) 서울 동대문구 천호대로 23 820호 (신설동,베르빌오피스텔)",
  "visits": 1
 },
 {
  "agency": "오지에이",
  "hq": "오지에이",
  "branch": "에스앤씨",
  "start": "2014-03-03",
  "fp": 0,
  "tel": "02-905-2345",
  "addr": "서울 강북구 도봉로89길 5 6층 (수유3동,윤성빌딩)",
  "addr_raw": "(010-74) 서울 강북구 도봉로89길 5 6층 (수유3동,윤성빌딩)",
  "visits": 1
 },
 {
  "agency": "오지에이",
  "hq": "오지에이",
  "branch": "진영종합",
  "start": "2014-03-03",
  "fp": 1,
  "tel": "02-6212-1394",
  "addr": "서울 강북구 오패산로77길 39 2층 2호 (번1동)",
  "addr_raw": "(010-65) 서울 강북구 오패산77길 39 2층 2호 (번1동)",
  "visits": 0
 },
 {
  "agency": "오지에이",
  "hq": "오지에이",
  "branch": "해피브릿지",
  "start": "2018-11-09",
  "fp": 0,
  "tel": "02-939-1101",
  "addr": "서울 도봉구 노해로62길 55 (창1동,한내빌딩) 401호",
  "addr_raw": "(014-83) 서울 도봉구 노해로62길 55 (창1동,한내빌딩) 401호",
  "visits": 1
 },
 {
  "agency": "유퍼스트보험마케팅",
  "hq": "유퍼스트 1",
  "branch": "강북",
  "start": "2013-04-17",
  "fp": 5,
  "tel": "02-766-4177",
  "addr": "서울 동대문구 왕산로 4 (신설동,동화빌딩) 304호",
  "addr_raw": "(025-82) 서울 동대문구 왕산로 4 (신설동,동화빌딩) 304호",
  "visits": 0
 },
 {
  "agency": "유퍼스트보험마케팅",
  "hq": "유퍼스트 1",
  "branch": "종로",
  "start": "2021-12-17",
  "fp": 13,
  "tel": "02-756-7013",
  "addr": "서울 종로구 난계로 247 (숭인2동,서진빌딩) 209호",
  "addr_raw": "(031-16) 서울 종로구 난계로 247 (숭인2동,서진빌딩) 209호",
  "visits": 0
 },
 {
  "agency": "유퍼스트보험마케팅",
  "hq": "유퍼스트 2",
  "branch": "두드림",
  "start": "2014-11-11",
  "fp": 3,
  "tel": "02-929-2848",
  "addr": "서울 종로구 난계로 247 (숭인2동,서진빌딩) 302호",
  "addr_raw": "(031-16) 서울 종로구 난계로 247 (숭인2동,서진빌딩) 302호",
  "visits": 0
 },
 {
  "agency": "인슈어스",
  "hq": "인슈어스",
  "branch": "인슈어스",
  "start": "2025-04-02",
  "fp": 6,
  "tel": "02-6166-8008",
  "addr": "서울 동대문구 황물로 5 (전농1동) 3층",
  "addr_raw": "(025-91) 서울 동대문구 황물로 5 (전농1동) 3층",
  "visits": 0
 },
 {
  "agency": "인카금융서비스",
  "hq": "인카금융서비스(주) 다이렉트",
  "branch": "다이렉트 골드지점",
  "start": "2018-07-12",
  "fp": 8,
  "tel": "02-3272-1133",
  "addr": "서울 강남구 선릉로162길 52 (청담동) 3층",
  "addr_raw": "(060-15) 서울 강남구 선릉로162길 52 (청담동) 3층",
  "visits": 0
 },
 {
  "agency": "인카금융서비스",
  "hq": "인카금융서비스(주) 다이렉트",
  "branch": "다이렉트미래전략",
  "start": "2023-11-23",
  "fp": 2,
  "tel": "02-598-8580",
  "addr": "서울 서초구 강남대로 148 (양재1동,상록빌딩) 4층",
  "addr_raw": "(067-48) 서울 서초구 강남대로 148 (양재1동,상록빌딩) 4층",
  "visits": 0
 },
 {
  "agency": "인카금융서비스",
  "hq": "인카금융서비스(주) 다이렉트",
  "branch": "다이렉트올림",
  "start": "2023-11-01",
  "fp": 0,
  "tel": "02-1688-6005",
  "addr": "서울 강남구 영동대로 602 (삼성1동) 미켈란107, 6층, 브이205",
  "addr_raw": "(060-83) 서울 강남구 영동대로 602 (삼성1동) 미켈란107, 6층, 브이205",
  "visits": 0
 },
 {
  "agency": "인카금융서비스",
  "hq": "인카금융서비스(주) 다이렉트",
  "branch": "다이렉트행복플렌",
  "start": "2024-06-10",
  "fp": 5,
  "tel": "02-3298-6827",
  "addr": "서울 동대문구 난계로30길 24 (신설동,신설동창성빌딩) 201호",
  "addr_raw": "(025-86) 서울 동대문구 난계로30길 24 (신설동,신설동창성빌딩) 201호",
  "visits": 1
 },
 {
  "agency": "인포유금융서비스",
  "hq": "인포유금융서비스",
  "branch": "램프",
  "start": "2023-10-27",
  "fp": 4,
  "tel": "02-3467-3900",
  "addr": "서울 강남구 언주로 432-8 (역삼2동,다보빌딩) 7층",
  "addr_raw": "(062-10) 서울 강남구 언주로 432-8 (역삼2동,다보빌딩) 7층",
  "visits": 0
 },
 {
  "agency": "인포유금융서비스",
  "hq": "인포유금융서비스",
  "branch": "서초",
  "start": "2016-09-01",
  "fp": 0,
  "tel": "010-5207-1125",
  "addr": "서울 서초구 강남대로6길 12 3층 (양재2동,진흥빌딩)",
  "addr_raw": "(067-87) 서울 서초구 강남대로6길 12 3층 (양재2동,진흥빌딩)",
  "visits": 0
 },
 {
  "agency": "인포유금융서비스",
  "hq": "인포유금융서비스",
  "branch": "재우인슈지점",
  "start": "2025-12-26",
  "fp": 1,
  "tel": "02-9831-0516",
  "addr": "서울 강북구 한천로 1062 (수유3동,삼창빌딩) 401호",
  "addr_raw": "(010-53) 서울 강북구 한천로 1062 (수유3동,삼창빌딩) 401호",
  "visits": 1
 },
 {
  "agency": "지금융코리아",
  "hq": "지금융코리아",
  "branch": "엔젤코리아",
  "start": "2024-11-13",
  "fp": 2,
  "tel": "070-7776-1004",
  "addr": "서울 도봉구 노해로 397-15 (창4동,백상빌딩) 1303호",
  "addr_raw": "(014-15) 서울 도봉구 노해로 397-15 (창4동,백상빌딩) 1303호",
  "visits": 0
 },
 {
  "agency": "지금융코리아",
  "hq": "지금융코리아",
  "branch": "이산강남",
  "start": "2025-10-23",
  "fp": 0,
  "tel": "02-6956-0095",
  "addr": "서울 강남구 테헤란로22길 11 (역삼1동,모닝타워) 502호",
  "addr_raw": "(062-36) 서울 강남구 테헤란로22길 11 (역삼1동,모닝타워) 502호",
  "visits": 1
 },
 {
  "agency": "지금융코리아",
  "hq": "지금융코리아",
  "branch": "이산역삼",
  "start": "2025-10-23",
  "fp": 11,
  "tel": "02-6956-0095",
  "addr": "서울 강남구 테헤란로22길 11 (역삼1동,모닝타워) 501호",
  "addr_raw": "(062-36) 서울 강남구 테헤란로22길 11 (역삼1동,모닝타워) 501호",
  "visits": 1
 },
 {
  "agency": "지에이스타금융서비스",
  "hq": "인코리아",
  "branch": "에스케이엠",
  "start": "2026-01-23",
  "fp": 1,
  "tel": "070-7261-1555",
  "addr": "서울 도봉구 노해로69길 21 (창4동) 9층 904호",
  "addr_raw": "(014-14) 서울 도봉구 노해로69길 21 (창4동) 9층 904호",
  "visits": 0
 },
 {
  "agency": "지에이스타금융서비스",
  "hq": "지앤비",
  "branch": "뉴에이스",
  "start": "2025-02-03",
  "fp": 1,
  "tel": "02-922-2541",
  "addr": "서울특별시 동대문구 난계로 250 411호(신설동, 경해빌딩)",
  "addr_raw": "(025-86) 서울특별시 동대문구 난계로 250 411호(신설동, 경해빌딩)",
  "visits": 1
 },
 {
  "agency": "지에이코리아",
  "hq": "GA코리아 강남본부 1",
  "branch": "에셋마스터제이더블유",
  "start": "2024-02-15",
  "fp": 0,
  "tel": "070-7287-3150",
  "addr": "서울 서초구 강남대로 221 (양재1동,양재역환승주차빌딩) 408호",
  "addr_raw": "(067-49) 서울 서초구 강남대로 221 (양재1동,양재역환승주차빌딩) 408호",
  "visits": 0
 },
 {
  "agency": "지에이코리아",
  "hq": "GA코리아 강남본부 1",
  "branch": "엠파이어뉴본",
  "start": "2021-02-26",
  "fp": 1,
  "tel": "02-3442-0126",
  "addr": "서울 강남구 역삼로73길 5 (대치4동) 4층",
  "addr_raw": "(061-96) 서울 강남구 역삼로73길 5 (대치4동) 4층",
  "visits": 0
 },
 {
  "agency": "지에이코리아",
  "hq": "GA코리아 강남본부 1",
  "branch": "엠파이어한넷트",
  "start": "2013-02-28",
  "fp": 3,
  "tel": "02-2256-7804",
  "addr": "서울 종로구 지봉로 29 (창신1동,금호파레스) 1804호",
  "addr_raw": "(031-21) 서울 종로구 지봉로 29 (창신1동,금호파레스) 1804호",
  "visits": 1
 },
 {
  "agency": "지에이코리아",
  "hq": "GA코리아 강남본부 2",
  "branch": "에셋플러스스타",
  "start": "2016-02-15",
  "fp": 0,
  "tel": "02-2677-8858",
  "addr": "서울 성동구 성수이로 147 (성수2가3동,아이에스비즈타워) 407호",
  "addr_raw": "(047-95) 서울 성동구 성수이로 147 (성수2가3동,아이에스비즈타워) 407호",
  "visits": 0
 },
 {
  "agency": "지에이코리아",
  "hq": "GA코리아 강남본부 2",
  "branch": "엔젤드림디에스리치",
  "start": "2023-11-24",
  "fp": 6,
  "tel": "02-711-8073",
  "addr": "서울 강남구 논현로87길 41 (역삼1동,신일유토빌) 305호",
  "addr_raw": "(062-35) 서울 강남구 논현로87길 41 (역삼1동,신일유토빌) 305호",
  "visits": 1
 },
 {
  "agency": "지에이코리아",
  "hq": "GA코리아 강북본부 1",
  "branch": "경덕방배",
  "start": "2019-01-22",
  "fp": 2,
  "tel": "02-584-0022",
  "addr": "서울 서초구 방배2동 451-7번지 삼원빌딩 302호",
  "addr_raw": "(066-92) 서울 서초구 방배2동 451-7번지 삼원빌딩 302호",
  "visits": 0
 },
 {
  "agency": "지에이코리아",
  "hq": "GA코리아 강북본부 1",
  "branch": "다진에셋",
  "start": "2013-05-10",
  "fp": 3,
  "tel": "02-981-9818",
  "addr": "서울 강북구 도봉로 126 (송중동) 302호",
  "addr_raw": "(011-64) 서울 강북구 도봉로 126 (송중동) 302호",
  "visits": 1
 },
 {
  "agency": "지에이코리아",
  "hq": "GA코리아 강북본부 1",
  "branch": "동부",
  "start": "2013-04-17",
  "fp": 13,
  "tel": "02-2208-7002",
  "addr": "서울특별시 중랑구 망우로 244 덕화빌딩 5층 ( 상봉동 )",
  "addr_raw": "(021-22) 서울특별시 중랑구 망우로 244 덕화빌딩 5층 ( 상봉동 )",
  "visits": 0
 },
 {
  "agency": "지에이코리아",
  "hq": "GA코리아 강북본부 1",
  "branch": "비에프북부",
  "start": "2025-09-26",
  "fp": 1,
  "tel": "010-7942-6179",
  "addr": "서울특별시 강북구 도봉로 328 , 913호(번동, 가든타워빌딩)",
  "addr_raw": "(010-62) 서울특별시 강북구 도봉로 328 , 913호(번동, 가든타워빌딩)",
  "visits": 1
 },
 {
  "agency": "지에이코리아",
  "hq": "GA코리아 강북본부 1",
  "branch": "비에프탑",
  "start": "2024-03-22",
  "fp": 0,
  "tel": "070-5300-2123",
  "addr": "서울 도봉구 마들로11가길 13-6 (창4동) 606호",
  "addr_raw": "(014-14) 서울 도봉구 마들로11가길 13-6 (창4동) 606호",
  "visits": 0
 },
 {
  "agency": "지에이코리아",
  "hq": "GA코리아 강북본부 1",
  "branch": "엔에스강북",
  "start": "2026-04-10",
  "fp": 1,
  "tel": "010-3103-8677",
  "addr": "서울특별시 강북구 월계로7길 67 3층(미아동)",
  "addr_raw": "(012-18) 서울특별시 강북구 월계로7길 67 3층(미아동)",
  "visits": 1
 },
 {
  "agency": "지에이코리아",
  "hq": "GA코리아 강북본부 1",
  "branch": "온강남",
  "start": "2013-05-10",
  "fp": 0,
  "tel": "02-2050-0601",
  "addr": "서울특별시 강남구 강남대로 84길 33 604호 (대우디오빌플러스)",
  "addr_raw": "(062-33) 서울특별시 강남구 강남대로 84길 33 604호 (대우디오빌플러스)",
  "visits": 1
 },
 {
  "agency": "지에이코리아",
  "hq": "GA코리아 강북본부 2",
  "branch": "에이플러스삼성",
  "start": "2016-08-04",
  "fp": 9,
  "tel": "02-552-5885",
  "addr": "서울 강남구 테헤란로78길 14-11 3층 (대치4동,돌채타워)",
  "addr_raw": "(061-94) 서울 강남구 테헤란로78길 14-11 3층 (대치4동,돌채타워)",
  "visits": 0
 },
 {
  "agency": "지에이코리아",
  "hq": "경인본부",
  "branch": "자산관리강남",
  "start": "2026-02-06",
  "fp": 0,
  "tel": "032-719-4240",
  "addr": "서울 서초구 나루터로 73 (잠원동,라전빌딩) 201호",
  "addr_raw": "(065-25) 서울 서초구 나루터로 73 (잠원동,라전빌딩) 201호",
  "visits": 0
 },
 {
  "agency": "케이엠아이에셋",
  "hq": "케이엠아이에셋",
  "branch": "강남금융센터",
  "start": "2018-02-05",
  "fp": 4,
  "tel": "02-8788-4625",
  "addr": "서울 서초구 강남대로 221 (양재1동,양재역환승주차장) 412호",
  "addr_raw": "(067-49) 서울 서초구 강남대로 221 (양재1동,양재역환승주차장) 412호",
  "visits": 0
 },
 {
  "agency": "케이엠아이에셋",
  "hq": "케이엠아이에셋",
  "branch": "모아드림",
  "start": "2024-10-02",
  "fp": 1,
  "tel": "070-9139-2951",
  "addr": "서울 강남구 테헤란로20길 18 (역삼1동) 10층 3호",
  "addr_raw": "(062-35) 서울 강남구 테헤란로20길 18 (역삼1동) 10층 3호",
  "visits": 1
 },
 {
  "agency": "케이엠아이에셋",
  "hq": "케이엠아이에셋",
  "branch": "미래플러스",
  "start": "2019-08-13",
  "fp": 1,
  "tel": "031-8003-6926",
  "addr": "서울 서초구 강남대로43길 16 (서초2동) 지하1층",
  "addr_raw": "(067-29) 서울 서초구 강남대로43길 16 (서초2동) 지하1층",
  "visits": 0
 },
 {
  "agency": "케이엠아이에셋",
  "hq": "케이엠아이에셋",
  "branch": "프라임",
  "start": "2017-10-10",
  "fp": 3,
  "tel": "02-470-5147",
  "addr": "서울 강남구 강남대로 354 (역삼1동,혜천빌딩) 1131호",
  "addr_raw": "(062-42) 서울 강남구 강남대로 354 (역삼1동,혜천빌딩) 1131호",
  "visits": 1
 },
 {
  "agency": "케이지에이에셋",
  "hq": "케이지에이에셋",
  "branch": "더블유에이엠",
  "start": "2026-04-14",
  "fp": 4,
  "tel": "02-6229-4000",
  "addr": "서울 동대문구 장한로 6 (장안1동,장안빌딩) 805호",
  "addr_raw": "(026-45) 서울 동대문구 장한로 6 (장안1동,장안빌딩) 805호",
  "visits": 1
 },
 {
  "agency": "케이지에이에셋",
  "hq": "케이지에이에셋",
  "branch": "바른",
  "start": "2020-07-29",
  "fp": 1,
  "tel": "02-568-5009",
  "addr": "서울 강남구 논현로85길 5-12 (역삼1동) 2층",
  "addr_raw": "(062-37) 서울 강남구 논현로85길 5-12 (역삼1동) 2층",
  "visits": 1
 },
 {
  "agency": "케이지에이에셋",
  "hq": "케이지에이에셋",
  "branch": "북부",
  "start": "2020-06-25",
  "fp": 1,
  "tel": "02-544-3611",
  "addr": "서울 도봉구 노해로 379 602호(창동)",
  "addr_raw": "(014-14) 서울 도봉구 노해로 379 602호(창동)",
  "visits": 0
 },
 {
  "agency": "케이지에이에셋",
  "hq": "케이지에이에셋 2",
  "branch": "에스엠",
  "start": "2015-05-25",
  "fp": 1,
  "tel": "02-6451-4411",
  "addr": "서울 성북구 동소문로34길 24 107호 (돈암동,삼성아파트)",
  "addr_raw": "(028-07) 서울 성북구 동소문로34길 24 107호 (돈암동,삼성아파트)",
  "visits": 1
 },
 {
  "agency": "케이지에이에셋",
  "hq": "케이지에이에셋 2",
  "branch": "프렌즈",
  "start": "2020-05-26",
  "fp": 1,
  "tel": "02-994-8770",
  "addr": "서울 동대문구 천호대로2길 23-3 (신설동) 403 -비호",
  "addr_raw": "(025-86) 서울 동대문구 천호대로2길 23-3 (신설동) 403 -비호",
  "visits": 0
 },
 {
  "agency": "케이지에이에셋",
  "hq": "케이지에이에셋 3",
  "branch": "강북제일지점",
  "start": "2022-04-29",
  "fp": 8,
  "tel": "02-908-8354",
  "addr": "서울 강북구 솔매로50길 3 (미아동) 2층",
  "addr_raw": "(011-57) 서울 강북구 솔매로50길 3 (미아동) 2층",
  "visits": 1
 },
 {
  "agency": "케이지에이에셋",
  "hq": "케이지에이에셋 3",
  "branch": "골든크로스",
  "start": "2017-05-26",
  "fp": 5,
  "tel": "02-3482-5527",
  "addr": "서울 서초구 방배천로6길 3-12 (방배2동,한두빌딩) 402호",
  "addr_raw": "(066-91) 서울 서초구 방배천로6길 3-12 (방배2동,한두빌딩) 402호",
  "visits": 0
 },
 {
  "agency": "케이지에이에셋",
  "hq": "케이지에이에셋 3",
  "branch": "왕십리",
  "start": "2024-02-02",
  "fp": 6,
  "tel": "02-2295-8470",
  "addr": "서울 성동구 고산자로 269 (도선동,신한넥스텔) 608호",
  "addr_raw": "(047-09) 서울 성동구 고산자로 269 (도선동,신한넥스텔) 608호",
  "visits": 1
 },
 {
  "agency": "케이지에이에셋",
  "hq": "케이지에이에셋 3",
  "branch": "정직한",
  "start": "2020-12-24",
  "fp": 3,
  "tel": "070-8671-7576",
  "addr": "서울 노원구 상계로 32 (상계6.7동) 노원역 보미 더 클래스 오피스텔, 801호",
  "addr_raw": "(016-89) 서울 노원구 상계로 32 (상계6.7동) 노원역 보미 더 클래스 오피스텔, 801호",
  "visits": 0
 },
 {
  "agency": "케이지에이에셋",
  "hq": "케이지에이에셋 강북본부1",
  "branch": "강북",
  "start": "2013-01-01",
  "fp": 7,
  "tel": "02-907-2081",
  "addr": "서울 강북구 도봉로 313 (수유3동,효성인텔리안오피스텔) 802호",
  "addr_raw": "(010-73) 서울 강북구 도봉로 313 (수유3동,효성인텔리안오피스텔) 802호",
  "visits": 1
 },
 {
  "agency": "케이지에이에셋",
  "hq": "케이지에이에셋 경인본부4",
  "branch": "지패밀리",
  "start": "2018-05-28",
  "fp": 2,
  "tel": "031-857-0369",
  "addr": "서울 성북구 정릉로 344 (정릉1동) 2층 202호",
  "addr_raw": "(028-17) 서울 성북구 정릉로 344 (정릉1동) 2층 202호",
  "visits": 1
 },
 {
  "agency": "케이탑자산관리",
  "hq": "케이탑자산관리",
  "branch": "노원",
  "start": "2014-04-01",
  "fp": 0,
  "tel": "02-930-8801",
  "addr": "서울 노원구 상계동730-5 일신프라자 503호",
  "addr_raw": "(017-62) 서울 노원구 상계동730-5 일신프라자 503호",
  "visits": 0
 },
 {
  "agency": "푸른신호등",
  "hq": "푸른신호등",
  "branch": "동대문",
  "start": "2014-08-07",
  "fp": 1,
  "tel": "02-2635-4604",
  "addr": "서울 도봉구 노해로69길 26 (창4동,창동시티월드) 1401동 2호",
  "addr_raw": "(014-15) 서울 도봉구 노해로69길 26 (창4동,창동시티월드) 1401동 2호",
  "visits": 0
 },
 {
  "agency": "푸른신호등",
  "hq": "푸른신호등",
  "branch": "수유",
  "start": "2014-08-07",
  "fp": 0,
  "tel": "02-905-7227",
  "addr": "서울 도봉구 노해로69길 26 (창4동,창동시티월드) 14층",
  "addr_raw": "(014-15) 서울 도봉구 노해로69길 26 (창4동,창동시티월드) 14층",
  "visits": 0
 },
 {
  "agency": "한국보험금융",
  "hq": "씨에스",
  "branch": "씨에스골드인에셋강북",
  "start": "2016-06-15",
  "fp": 1,
  "tel": "02-6671-5111",
  "addr": "서울 강북구 덕릉로 101 702호 (번1동,서울빌딩)",
  "addr_raw": "(010-69) 서울 강북구 덕릉로 101 702호 (번1동,서울빌딩)",
  "visits": 1
 },
 {
  "agency": "한국보험금융",
  "hq": "씨에스",
  "branch": "씨에스노원",
  "start": "2016-06-15",
  "fp": 0,
  "tel": "02-932-1716",
  "addr": "서울 노원구 동일로 1426 305호 (상계10동,미도빌딩)",
  "addr_raw": "(016-94) 서울 노원구 동일로 1426 305호 (상계10동,미도빌딩)",
  "visits": 0
 },
 {
  "agency": "한국보험금융",
  "hq": "씨에스",
  "branch": "씨에스드림위즈세종",
  "start": "2017-06-23",
  "fp": 0,
  "tel": "02-2138-0155",
  "addr": "서울 서초구 논현로 87 (양재2동,삼호물산빌딩) 501호",
  "addr_raw": "(067-75) 서울 서초구 논현로 87 (양재2동,삼호물산빌딩) 501호",
  "visits": 0
 },
 {
  "agency": "한국보험금융",
  "hq": "씨에스",
  "branch": "씨에스리치플러스",
  "start": "2016-06-15",
  "fp": 5,
  "tel": "02-563-6932",
  "addr": "서울 강남구 역삼로 113 오성빌딩 608호",
  "addr_raw": "(062-41) 서울 강남구 역삼로 113 오성빌딩 608호",
  "visits": 1
 },
 {
  "agency": "한국보험금융",
  "hq": "씨에스",
  "branch": "씨에스피앤제이",
  "start": "2018-12-11",
  "fp": 2,
  "tel": "02-501-9936",
  "addr": "서울 강남구 역삼로 114 (역삼1동,현죽빌딩) 835호",
  "addr_raw": "(062-52) 서울 강남구 역삼로 114 (역삼1동,현죽빌딩) 835호",
  "visits": 1
 },
 {
  "agency": "한국보험금융",
  "hq": "에스에이치글로벌",
  "branch": "더에스에이지",
  "start": "2024-05-28",
  "fp": 35,
  "tel": "02-3142-9849",
  "addr": "서울 서초구 강남대로 527 (반포1동,브랜드칸타워) 10층",
  "addr_raw": "(065-36) 서울 서초구 강남대로 527 (반포1동,브랜드칸타워) 10층",
  "visits": 0
 },
 {
  "agency": "한국보험금융",
  "hq": "코인스금융서비스",
  "branch": "골든",
  "start": "2015-04-16",
  "fp": 0,
  "tel": "02-3443-0578",
  "addr": "서울 강남구 선릉로90길 38 (대치4동,현민타워) 6층",
  "addr_raw": "(061-93) 서울 강남구 선릉로90길 38 (대치4동,현민타워) 6층",
  "visits": 0
 },
 {
  "agency": "한국보험금융",
  "hq": "코인스금융서비스",
  "branch": "새한에셋라온",
  "start": "2015-04-16",
  "fp": 0,
  "tel": "02-6959-0119",
  "addr": "서울 서초구 서초대로 397 2707호 (서초4동,부띠크모나코)",
  "addr_raw": "(066-16) 서울 서초구 서초대로 397 2707호 (서초4동,부띠크모나코)",
  "visits": 0
 },
 {
  "agency": "한국보험금융",
  "hq": "코인스금융서비스",
  "branch": "새한에셋신성",
  "start": "2015-04-16",
  "fp": 0,
  "tel": "02-583-0312",
  "addr": "서울 서초구 방배천로2길 39-10 3층 (방배2동)",
  "addr_raw": "(066-93) 서울 서초구 방배천로2길 39-10 3층 (방배2동)",
  "visits": 0
 },
 {
  "agency": "한국보험금융",
  "hq": "코인스금융서비스",
  "branch": "에이엠아이",
  "start": "2015-04-16",
  "fp": 1,
  "tel": "02-538-8188",
  "addr": "서울 강남구 강남대로 320 13층 (역삼1동,황화빌딩)",
  "addr_raw": "(062-52) 서울 강남구 강남대로 320 13층 (역삼1동,황화빌딩)",
  "visits": 1
 },
 {
  "agency": "한국보험금융",
  "hq": "코인스금융서비스",
  "branch": "원나이스",
  "start": "2015-04-29",
  "fp": 0,
  "tel": "02-2252-2838",
  "addr": "서울 동대문구 천호대로 295 (답십리1동,우창프라자아파트) 901호",
  "addr_raw": "(026-04) 서울 동대문구 천호대로 295 (답십리1동,우창프라자아파트) 901호",
  "visits": 0
 },
 {
  "agency": "한국보험금융",
  "hq": "코인스금융서비스 2",
  "branch": "CS강남",
  "start": "2016-04-14",
  "fp": 0,
  "tel": "02-553-6811",
  "addr": "서울 강남구 논현로81길 12 202호 (역삼1동,조앤리빌딩)",
  "addr_raw": "(062-37) 서울 강남구 논현로81길 12 202호 (역삼1동,조앤리빌딩)",
  "visits": 1
 },
 {
  "agency": "한국보험금융",
  "hq": "코인스금융서비스 2",
  "branch": "메타",
  "start": "2025-01-13",
  "fp": 11,
  "tel": "02-1522-3676",
  "addr": "서울 서초구 동작대로 62 (방배2동,용진빌딩) 446호",
  "addr_raw": "(066-77) 서울 서초구 동작대로 62 (방배2동,용진빌딩) 446호",
  "visits": 0
 },
 {
  "agency": "한국보험금융",
  "hq": "코인스금융서비스 2",
  "branch": "비엠티",
  "start": "2017-06-02",
  "fp": 0,
  "tel": "02-455-0094",
  "addr": "서울 강남구 헌릉로571길 41 세곡동 B02호",
  "addr_raw": "(063-76) 서울 강남구 헌릉로571길 41 세곡동 B02호",
  "visits": 0
 },
 {
  "agency": "한국보험금융",
  "hq": "코인스금융서비스 2",
  "branch": "빅토리",
  "start": "2024-01-16",
  "fp": 4,
  "tel": "070-4070-0708",
  "addr": "서울 성북구 보문로 137 (보문동2가) 3층",
  "addr_raw": "(028-71) 서울 성북구 보문로 137 (보문동2가) 3층",
  "visits": 1
 },
 {
  "agency": "한국보험금융",
  "hq": "코인스금융서비스 2",
  "branch": "삼성세무",
  "start": "2017-04-20",
  "fp": 2,
  "tel": "02-2208-0567",
  "addr": "서울 중랑구 용마산로115길 108 (망우본동,안빌딩) 8층 804호",
  "addr_raw": "(021-63) 서울 중랑구 용마산로115길 108 (망우본동,안빌딩) 8층 804호",
  "visits": 0
 },
 {
  "agency": "한국보험금융",
  "hq": "코인스금융서비스 2",
  "branch": "선릉",
  "start": "2019-07-01",
  "fp": 0,
  "tel": "02-0563-2014",
  "addr": "서울 강남구 테헤란로52길 21 (역삼2동,역삼동벤처빌딩) 4층 S31호",
  "addr_raw": "(062-12) 서울 강남구 테헤란로52길 21 (역삼2동,역삼동벤처빌딩) 4층 S31호",
  "visits": 0
 },
 {
  "agency": "한국보험금융",
  "hq": "코인스금융서비스 2",
  "branch": "익투스",
  "start": "2024-07-10",
  "fp": 4,
  "tel": "02-466-8924",
  "addr": "서울 성동구 성수일로10길 33 (성수2가3동,기독교대한성결교회) 911호",
  "addr_raw": "(047-93) 서울 성동구 성수일로10길 33 (성수2가3동,기독교대한성결교회) 911호",
  "visits": 0
 },
 {
  "agency": "한국보험금융",
  "hq": "코인스금융서비스 2",
  "branch": "케이씨글로벌",
  "start": "2017-05-29",
  "fp": 10,
  "tel": "02-581-5123",
  "addr": "서울 서초구 방배천로18길 6 (방배2동,인성빌딩) 501호",
  "addr_raw": "(066-77) 서울 서초구 방배천로18길 6 (방배2동,인성빌딩) 501호",
  "visits": 0
 },
 {
  "agency": "한국보험금융",
  "hq": "코인스금융서비스 2",
  "branch": "택스앤에셋",
  "start": "2017-11-28",
  "fp": 32,
  "tel": "02-2051-9399",
  "addr": "서울 강남구 테헤란로7길 12 허바허바빌딩 505호(역삼동)",
  "addr_raw": "(061-33) 서울 강남구 테헤란로7길 12 허바허바빌딩 505호(역삼동)",
  "visits": 1
 },
 {
  "agency": "한국보험금융",
  "hq": "코인스금융서비스 2",
  "branch": "테헤란",
  "start": "2023-04-14",
  "fp": 7,
  "tel": "02-569-2022",
  "addr": "서울 강남구 선릉로100길 30 (삼성2동,유니콘빌딩) 201호",
  "addr_raw": "(061-61) 서울 강남구 선릉로100길 30 (삼성2동,유니콘빌딩) 201호",
  "visits": 0
 },
 {
  "agency": "한국보험금융",
  "hq": "코인스금융서비스 2",
  "branch": "피아이씨",
  "start": "2020-03-23",
  "fp": 0,
  "tel": "02-0498-6658",
  "addr": "서울 성동구 성수이로 147 (성수2가3동,아이에스비즈타워) 407호",
  "addr_raw": "(047-95) 서울 성동구 성수이로 147 (성수2가3동,아이에스비즈타워) 407호",
  "visits": 0
 },
 {
  "agency": "한국재무설계",
  "hq": "아이에프피",
  "branch": "아이에프피",
  "start": "2013-09-11",
  "fp": 0,
  "tel": "02-6711-6000",
  "addr": "서울 강남구 테헤란로107길 11 2층 (삼성1동,성보타운)",
  "addr_raw": "(061-73) 서울 강남구 테헤란로107길 11 2층 (삼성1동,성보타운)",
  "visits": 0
 },
 {
  "agency": "한국재무설계",
  "hq": "한국재무설계닥터인",
  "branch": "한국재무설계닥터인",
  "start": "2013-01-01",
  "fp": 0,
  "tel": "02-6711-6000",
  "addr": "서울 강남구 테헤란로107길 11 2층 (삼성1동,성보타운)",
  "addr_raw": "(061-73) 서울 강남구 테헤란로107길 11 2층 (삼성1동,성보타운)",
  "visits": 0
 },
 {
  "agency": "한국재무설계",
  "hq": "한국재무설계중소기업",
  "branch": "한국재무설계중소기업",
  "start": "2013-01-01",
  "fp": 0,
  "tel": "02-6711-6000",
  "addr": "서울 강남구 테헤란로107길 11 2층 (삼성1동,성보타운)",
  "addr_raw": "(061-73) 서울 강남구 테헤란로107길 11 2층 (삼성1동,성보타운)",
  "visits": 0
 },
 {
  "agency": "한솔금융서비스",
  "hq": "한솔금융서비스",
  "branch": "넘버원지사",
  "start": "2019-12-09",
  "fp": 0,
  "tel": "02-989-9665",
  "addr": "서울 강북구 송중동 35-27번지 3층",
  "addr_raw": "(012-20) 서울 강북구 송중동 35-27번지 3층",
  "visits": 1
 },
 {
  "agency": "한화라이프랩",
  "hq": "한화라이프랩",
  "branch": "강북",
  "start": "2021-08-10",
  "fp": 0,
  "tel": "02-3297-3943",
  "addr": "서울 강북구 도봉로 325 (수유3동,수성타워) 8층",
  "addr_raw": "(010-73) 서울 강북구 도봉로 325 (수유3동,수성타워) 8층",
  "visits": 1
 },
 {
  "agency": "한화라이프랩",
  "hq": "한화라이프랩",
  "branch": "나이스",
  "start": "2022-07-07",
  "fp": 0,
  "tel": "02-2168-6311",
  "addr": "서울 노원구 상계로 59 (상계10동,동익빌딩) 8층 2호",
  "addr_raw": "(016-94) 서울 노원구 상계로 59 (상계10동,동익빌딩) 8층 2호",
  "visits": 0
 },
 {
  "agency": "한화라이프랩",
  "hq": "한화라이프랩",
  "branch": "리치디바인",
  "start": "2023-09-25",
  "fp": 0,
  "tel": "02-552-9758",
  "addr": "서울 강남구 봉은사로 524 (삼성동) 코엑스인터컨티넨탈서울 비265,266호",
  "addr_raw": "(061-64) 서울 강남구 봉은사로 524 (삼성동) 코엑스인터컨티넨탈서울 비265,266호",
  "visits": 0
 },
 {
  "agency": "한화라이프랩",
  "hq": "한화라이프랩",
  "branch": "서초",
  "start": "2018-09-05",
  "fp": 0,
  "tel": "02-565-5435",
  "addr": "서울 서초구 방배천로2길 156층(오륜빌딩)",
  "addr_raw": "(066-93) 서울 서초구 방배천로2길 156층(오륜빌딩)",
  "visits": 0
 },
 {
  "agency": "한화라이프랩",
  "hq": "한화라이프랩",
  "branch": "성온",
  "start": "2025-12-04",
  "fp": 7,
  "tel": "02-1588-1331",
  "addr": "서울 성북구 안암로5길 22 (안암동4가,청우빌딩) 401호",
  "addr_raw": "(028-57) 서울 성북구 안암로5길 22 (안암동4가,청우빌딩) 401호",
  "visits": 1
 },
 {
  "agency": "한화라이프랩",
  "hq": "한화라이프랩",
  "branch": "에이치에프피강남에프시",
  "start": "2022-03-10",
  "fp": 0,
  "tel": "02-569-5562",
  "addr": "서울 강남구 테헤란로 317 (역삼1동,동훈타워) 9층",
  "addr_raw": "(061-51) 서울 강남구 테헤란로 317 (역삼1동,동훈타워) 9층",
  "visits": 0
 },
 {
  "agency": "한화라이프랩",
  "hq": "한화라이프랩",
  "branch": "코리아",
  "start": "2021-03-19",
  "fp": 1,
  "tel": "02-2249-6658",
  "addr": "서울 성동구 천호대로 432 (용답동,금풍빌딩) 10층",
  "addr_raw": "(048-08) 서울 성동구 천호대로 432 (용답동,금풍빌딩) 10층",
  "visits": 1
 },
 {
  "agency": "한화라이프랩",
  "hq": "한화라이프랩",
  "branch": "코스파",
  "start": "2021-08-10",
  "fp": 0,
  "tel": "02-552-1013",
  "addr": "서울 강남구 역삼로9길 28 (역삼1동,도원빌딩) 2층",
  "addr_raw": "(062-45) 서울 강남구 역삼로9길 28 (역삼1동,도원빌딩) 2층",
  "visits": 1
 },
 {
  "agency": "한화라이프랩",
  "hq": "한화라이프랩",
  "branch": "한화라이프랩동선지점",
  "start": "2020-03-27",
  "fp": 0,
  "tel": "02-2168-6311",
  "addr": "서울 노원구 동일로 1419 (상계6.7동, 디와이홀딩스㈜ 빌딩) 6층 한화라이프에셋 동선지점",
  "addr_raw": "(016-89) 서울 노원구 동일로 1419 (상계6.7동, 디와이홀딩스㈜ 빌딩) 6층 한화라이프에셋 동선지점",
  "visits": 0
 },
 {
  "agency": "한화라이프랩",
  "hq": "한화라이프랩",
  "branch": "한화라이프랩리더스지점",
  "start": "2020-04-27",
  "fp": 6,
  "tel": "02-2256-7780",
  "addr": "서울 노원구 동일로230가길 57 (상계1동,티에프그룹빌딩) 6층",
  "addr_raw": "(016-30) 서울 노원구 동일로230가길 57 (상계1동,티에프그룹빌딩) 6층",
  "visits": 1
 },
 {
  "agency": "한화라이프랩",
  "hq": "한화라이프랩",
  "branch": "한화법인서울",
  "start": "2022-03-15",
  "fp": 2,
  "tel": "02-775-5276",
  "addr": "서울 종로구 삼일대로 447 (경운동) 6층 603호",
  "addr_raw": "(031-48) 서울 종로구 삼일대로 447 (경운동) 6층 603호",
  "visits": 1
 },
 {
  "agency": "한화라이프랩",
  "hq": "한화라이프랩",
  "branch": "한화퍼스트",
  "start": "2020-11-18",
  "fp": 0,
  "tel": "02-739-5802",
  "addr": "서울 종로구 삼일대로 447 (경운동,부남빌딩) 6층",
  "addr_raw": "(031-48) 서울 종로구 삼일대로 447 (경운동,부남빌딩) 6층",
  "visits": 1
 },
 {
  "agency": "한화생명금융서비스",
  "hq": "한화생명금융서비스",
  "branch": "아너스울림지점",
  "start": "2025-04-29",
  "fp": 21,
  "tel": "070-8693-2465",
  "addr": "서울 강남구 봉은사로30길 62 (역삼1동,영우빌딩) 4층",
  "addr_raw": "(061-40) 서울 강남구 봉은사로30길 62 (역삼1동,영우빌딩) 4층",
  "visits": 0
 },
 {
  "agency": "한화생명금융서비스",
  "hq": "한화생명금융서비스",
  "branch": "퍼스트지점",
  "start": "2023-11-27",
  "fp": 9,
  "tel": "02-6949-6623",
  "addr": "서울 종로구 청계천로 71 (관철동,계원빌딩) 1306호",
  "addr_raw": "(031-89) 서울 종로구 청계천로 71 (관철동,계원빌딩) 1306호",
  "visits": 1
 },
 {
  "agency": "한화피플라이프",
  "hq": "한화피플라이프",
  "branch": "노바지점",
  "start": "2026-01-12",
  "fp": 93,
  "tel": "02-6715-0503",
  "addr": "서울 강남구 논현로 515 (역삼1동,아승빌딩) 6층",
  "addr_raw": "(061-31) 서울 강남구 논현로 515 (역삼1동,아승빌딩) 6층",
  "visits": 0
 },
 {
  "agency": "한화피플라이프",
  "hq": "한화피플라이프",
  "branch": "세종티에스아이",
  "start": "2024-12-09",
  "fp": 43,
  "tel": "02-6906-9104",
  "addr": "서울 서초구 서초대로 2 (방배4동,이수파이브) 11층",
  "addr_raw": "(066-75) 서울 서초구 서초대로 2 (방배4동,이수파이브) 11층",
  "visits": 0
 },
 {
  "agency": "한화피플라이프",
  "hq": "한화피플라이프",
  "branch": "제이원",
  "start": "2023-04-10",
  "fp": 57,
  "tel": "02-2086-8687",
  "addr": "서울 서초구 동작대로 86 (방배2동,동주빌딩) 2층",
  "addr_raw": "(066-75) 서울 서초구 동작대로 86 (방배2동,동주빌딩) 2층",
  "visits": 0
 },
 {
  "agency": "한화피플라이프",
  "hq": "한화피플라이프",
  "branch": "케이원",
  "start": "2021-12-20",
  "fp": 46,
  "tel": "02-2086-8685",
  "addr": "서울 서초구 동작대로 86 (방배2동,동주빌딩) 8층",
  "addr_raw": "(066-75) 서울 서초구 동작대로 86 (방배2동,동주빌딩) 8층",
  "visits": 0
 },
 {
  "agency": "한화피플라이프",
  "hq": "한화피플라이프",
  "branch": "티앨리",
  "start": "2025-03-13",
  "fp": 0,
  "tel": "02-2162-7765",
  "addr": "서울 서초구 서초대로 2 (방배4동,이수파이브) 10층",
  "addr_raw": "(066-75) 서울 서초구 서초대로 2 (방배4동,이수파이브) 10층",
  "visits": 0
 },
 {
  "agency": "한화피플라이프",
  "hq": "한화피플라이프",
  "branch": "파라다이스",
  "start": "2022-04-12",
  "fp": 13,
  "tel": "02-2086-8719",
  "addr": "서울 서초구 방배천로2길 15 (방배2동) 6층 601호",
  "addr_raw": "(066-93) 서울 서초구 방배천로2길 15 (방배2동) 6층 601호",
  "visits": 0
 },
 {
  "agency": "한화피플라이프",
  "hq": "한화피플라이프",
  "branch": "플랜씨",
  "start": "2018-10-30",
  "fp": 15,
  "tel": "02-2038-8001",
  "addr": "서울특별시 서초구 서초대로 59 7층(방배동,경은빌딩)",
  "addr_raw": "(065-70) 서울특별시 서초구 서초대로 59 7층(방배동,경은빌딩)",
  "visits": 0
 },
 {
  "agency": "한화피플라이프",
  "hq": "한화피플라이프",
  "branch": "피엔씨",
  "start": "2024-11-12",
  "fp": 4,
  "tel": "02-2088-5194",
  "addr": "서울 서초구 서초대로 146 (방배1동) 지하1층",
  "addr_raw": "(066-61) 서울 서초구 서초대로 146 (방배1동) 지하1층",
  "visits": 0
 }
]